aiogoogle/__init__.py
aiogoogle/__version__.py
aiogoogle/client.py
aiogoogle/data.py
aiogoogle/excs.py
aiogoogle/models.py
aiogoogle/py.typed
aiogoogle/resource.py
aiogoogle/utils.py
aiogoogle/validate.py
aiogoogle/auth/__init__.py
aiogoogle/auth/creds.py
aiogoogle/auth/data.py
aiogoogle/auth/managers.py
aiogoogle/auth/utils.py
aiogoogle/sessions/__init__.py
aiogoogle/sessions/abc.py
aiogoogle/sessions/aiohttp_session.py
aiogoogle/sessions/common.py
aiogoogle/sessions/curio_asks_session.py
aiogoogle/sessions/trio_asks_session.py
aiogoogle-5.16.0.dist-info/licenses/LICENSE
aiogoogle-5.16.0.dist-info/METADATA
aiogoogle-5.16.0.dist-info/WHEEL
aiogoogle-5.16.0.dist-info/top_level.txt
aiogoogle-5.16.0.dist-info/RECORD
