Metadata-Version: 2.4
Name: aiogoogle
Version: 5.16.0
Summary: Async Google API client
Home-page: https://github.com/omarryhan/aiogoogle
Author: Omar Ryhan
Author-email: omarryhan@gmail.com
License: MIT
Classifier: Programming Language :: Python :: 3.7
Classifier: Operating System :: OS Independent
License-File: LICENSE
Requires-Dist: aiohttp
Requires-Dist: aiofiles
Requires-Dist: google-auth
Requires-Dist: tonyg-rfc3339
Requires-Dist: async-timeout
Requires-Dist: contextvars; python_version < "3.7"
Provides-Extra: curio-asks
Requires-Dist: asks; extra == "curio-asks"
Requires-Dist: curio; extra == "curio-asks"
Provides-Extra: trio-asks
Requires-Dist: asks; extra == "trio-asks"
Requires-Dist: trio; extra == "trio-asks"
Dynamic: author
Dynamic: author-email
Dynamic: classifier
Dynamic: description
Dynamic: description-content-type
Dynamic: home-page
Dynamic: license
Dynamic: license-file
Dynamic: provides-extra
Dynamic: requires-dist
Dynamic: summary
